reader/__init__.py
reader/__main__.py
reader/config.cfg
reader/feed.py
reader/viewer.py
reader_test_rachit_2-1.0.1.dist-info/METADATA
reader_test_rachit_2-1.0.1.dist-info/WHEEL
reader_test_rachit_2-1.0.1.dist-info/entry_points.txt
reader_test_rachit_2-1.0.1.dist-info/top_level.txt
reader_test_rachit_2-1.0.1.dist-info/RECORD
