Metadata-Version: 2.1
Name: reader-test-rachit-2
Version: 1.0.1
Summary: UNKNOWN
Home-page: UNKNOWN
Author: rachitmishra25
Author-email: rachit.mishra94@gmail.com
License: UNKNOWN
Platform: UNKNOWN
Classifier: Programming Language :: Python :: 3
Classifier: Programming Language :: Python :: 3.7
Requires-Dist: feedparser
Requires-Dist: html2text
Requires-Dist: importlib-resources
Requires-Dist: typing
